rsyslog_postgres_tools/__init__.py
rsyslog_postgres_tools/main.py
rsyslog_postgres_tools-0.1.0.data/scripts/run_rp_tools.py
rsyslog_postgres_tools-0.1.0.dist-info/LICENSE
rsyslog_postgres_tools-0.1.0.dist-info/METADATA
rsyslog_postgres_tools-0.1.0.dist-info/WHEEL
rsyslog_postgres_tools-0.1.0.dist-info/top_level.txt
rsyslog_postgres_tools-0.1.0.dist-info/RECORD
